LICENSE
MANIFEST.in
README.rst
setup.py
django_maccman.egg-info/PKG-INFO
django_maccman.egg-info/SOURCES.txt
django_maccman.egg-info/dependency_links.txt
django_maccman.egg-info/requires.txt
django_maccman.egg-info/top_level.txt
maccman/__init__.py
maccman/admin.py
maccman/apps.py
maccman/models.py
maccman/tests.py
maccman/views.py
maccman/migrations/0001_initial.py
maccman/migrations/0002_views.py
maccman/migrations/__init__.py
maccman/support/views.sql